Metadata-Version: 1.1
Name: plotille
Version: 3.4
Summary: Plot in the terminal using braille dots.
Home-page: https://github.com/tammoippen/plotille
Author: Tammo Ippen
Author-email: tammo.ippen@posteo.de
License: MIT
Download-URL: https://github.com/tammoippen/plotille/archive/v3.4.tar.gz
Keywords: plot,scatter,histogram,terminal,braille,unicode,timeseries
Platform: UNKNOWN
Classifier: Environment :: Console
Classifier: License :: OSI Approved :: MIT License
Classifier: Intended Audience :: Science/Research
Classifier: Programming Language :: Python
Classifier: Programming Language :: Python :: 2.7
Classifier: Programming Language :: Python :: 3
Classifier: Programming Language :: Python :: 3.5
Classifier: Programming Language :: Python :: 3.6
Classifier: Programming Language :: Python :: Implementation :: CPython
Classifier: Programming Language :: Python :: Implementation :: PyPy
Classifier: Topic :: Scientific/Engineering :: Visualization
Classifier: Topic :: Terminals
